.gitignore
MANIFEST.in
Makefile
README.rst
RELEASE-VERSION
gitversion.py
pyproject.toml
quickyaml.c
setup.py
test.py
version.h
debian/README
debian/changelog
debian/control
debian/copyright
debian/docs
debian/rules
debian/source/format
nicos_quickyaml.egg-info/PKG-INFO
nicos_quickyaml.egg-info/SOURCES.txt
nicos_quickyaml.egg-info/dependency_links.txt
nicos_quickyaml.egg-info/requires.txt
nicos_quickyaml.egg-info/top_level.txt