Metadata-Version: 2.1
Name: nicos-quickyaml
Version: 1.3.2
Summary: NICOS quick but restricted YAML dumper module
Author: Georg Brandl
Author-email: g.brandl@fz-juelich.de
License: GPL-2.0+
Requires-Dist: numpy
